StateMachineLibrary/__init__.py
StateMachineLibrary/exceptions.py
StateMachineLibrary/facade.py
StateMachineLibrary/interface.py
StateMachineLibrary/state_machine.py
StateMachineLibrary/store.py
StateMachineLibrary/utils.py
robotframework_statemachinelibrary-2.0.0.dist-info/LICENSE.txt
robotframework_statemachinelibrary-2.0.0.dist-info/METADATA
robotframework_statemachinelibrary-2.0.0.dist-info/WHEEL
robotframework_statemachinelibrary-2.0.0.dist-info/top_level.txt
robotframework_statemachinelibrary-2.0.0.dist-info/RECORD
