Metadata-Version: 2.1
Name: robotframework-statemachinelibrary
Version: 2.0.0
Summary: Robot Framework State Machine Library
Author: marcinooo
License: The MIT License (MIT)
Project-URL: Homepage, https://github.com/marcinooo/robot-framework-state-machine
Project-URL: Issues, https://github.com/marcinooo/robot-framework-state-machine/issues
Classifier: Programming Language :: Python :: 3
Classifier: License :: OSI Approved :: MIT License
Classifier: Operating System :: OS Independent
Requires-Python: >=3.6
License-File: LICENSE.txt
Requires-Dist: robotframework
